simusys/__init__.py
simusys-0.1.dist-info/METADATA
simusys-0.1.dist-info/WHEEL
simusys-0.1.dist-info/top_level.txt
simusys-0.1.dist-info/RECORD
